dep_tree/main.py
python_dep_tree-0.19.9.dist-info/METADATA
python_dep_tree-0.19.9.dist-info/WHEEL
python_dep_tree-0.19.9.dist-info/entry_points.txt
python_dep_tree-0.19.9.dist-info/RECORD
