Metadata-Version: 2.1
Name: python-dep-tree
Version: 0.19.9
Summary: Python wrapper for Dep Tree https://github.com/gabotechs/dep-tree
Author: gabotechs
Author-email: gb.mt.me@gmail.com
Requires-Python: >=3.7,<4.0
Classifier: Programming Language :: Python :: 3
Classifier: Programming Language :: Python :: 3.7
Classifier: Programming Language :: Python :: 3.8
Classifier: Programming Language :: Python :: 3.9
Classifier: Programming Language :: Python :: 3.10
Classifier: Programming Language :: Python :: 3.11
Classifier: Programming Language :: Python :: 3.12
